l2p/__init__.py
l2p/domain_builder.py
l2p/feedback_builder.py
l2p/llm_builder.py
l2p/prompt_builder.py
l2p/task_builder.py
l2p/utils/__init__.py
l2p/utils/pddl_parser.py
l2p/utils/pddl_planner.py
l2p/utils/pddl_types.py
l2p/utils/pddl_validator.py
l2p/utils/utils.py
lang2pddl-0.1.6.dist-info/LICENSE
lang2pddl-0.1.6.dist-info/METADATA
lang2pddl-0.1.6.dist-info/WHEEL
lang2pddl-0.1.6.dist-info/top_level.txt
lang2pddl-0.1.6.dist-info/RECORD
