Metadata-Version: 2.1
Name: lang2pddl
Version: 0.1.6
Summary: Library to connect LLMs and planning tasks
Home-page: https://github.com/AI-Planning/l2p
Author: Marcus Tantakoun
Author-email: mtantakoun@gmail.com
License: MIT
Classifier: Programming Language :: Python :: 3
Classifier: License :: OSI Approved :: MIT License
Classifier: Operating System :: OS Independent
Requires-Python: >=3.10
License-File: LICENSE
Requires-Dist: retry
Requires-Dist: pddl
Requires-Dist: typing_extensions
